discord/ext/ui/__init__.py
discord/ext/ui/alert.py
discord/ext/ui/button.py
discord/ext/ui/custom.py
discord/ext/ui/item.py
discord/ext/ui/message.py
discord/ext/ui/modal.py
discord/ext/ui/observable_object.py
discord/ext/ui/page.py
discord/ext/ui/provider.py
discord/ext/ui/published.py
discord/ext/ui/select.py
discord/ext/ui/state.py
discord/ext/ui/tracker.py
discord/ext/ui/utils.py
discord/ext/ui/view.py
discord/ext/ui/combine/__init__.py
discord/ext/ui/combine/async_publisher.py
discord/ext/ui/combine/just.py
discord/ext/ui/combine/publisher.py
discord/ext/ui/combine/subject.py
discord/ext/ui/combine/url_request.py
discord_ext_ui-3.1.9.dist-info/LICENSE
discord_ext_ui-3.1.9.dist-info/METADATA
discord_ext_ui-3.1.9.dist-info/WHEEL
discord_ext_ui-3.1.9.dist-info/top_level.txt
discord_ext_ui-3.1.9.dist-info/RECORD
